robustneldermead/__init__.py
robustneldermead/neldermead.py
robustneldermead-1.4.data/data/LICENSE.txt
robustneldermead-1.4.dist-info/LICENSE.txt
robustneldermead-1.4.dist-info/METADATA
robustneldermead-1.4.dist-info/WHEEL
robustneldermead-1.4.dist-info/top_level.txt
robustneldermead-1.4.dist-info/RECORD
